{
	"configurations" : 
	[
		{
			"directories" : 
			[
				{
					"build" : ".",
					"jsonFile" : "directory-.-Debug-f5ebdc15457944623624.json",
					"minimumCMakeVersion" : 
					{
						"string" : "3.22"
					},
					"projectIndex" : 0,
					"source" : ".",
					"targetIndexes" : 
					[
						0
					]
				}
			],
			"name" : "Debug",
			"projects" : 
			[
				{
					"directoryIndexes" : 
					[
						0
					],
					"name" : "cashRegister",
					"targetIndexes" : 
					[
						0
					]
				}
			],
			"targets" : 
			[
				{
					"directoryIndex" : 0,
					"id" : "cashRegister::@6890427a1f51a3e7e1df",
					"jsonFile" : "target-cashRegister-Debug-41a5f34b9ac9783132f9.json",
					"name" : "cashRegister",
					"projectIndex" : 0
				}
			]
		}
	],
	"kind" : "codemodel",
	"paths" : 
	{
		"build" : "/Users/simeonmarchand/Projects/CPPRasmussen/cashRegister/cmake-build-debug",
		"source" : "/Users/simeonmarchand/Projects/CPPRasmussen/cashRegister"
	},
	"version" : 
	{
		"major" : 2,
		"minor" : 3
	}
}
